archive/play.py
ntlk_mcp-0.1.0.dist-info/METADATA
ntlk_mcp-0.1.0.dist-info/WHEEL
ntlk_mcp-0.1.0.dist-info/top_level.txt
ntlk_mcp-0.1.0.dist-info/RECORD
